better_web3/__init__.py
better_web3/batch_call.py
better_web3/chain.py
better_web3/contract/__init__.py
better_web3/contract/_abi.py
better_web3/contract/_paths.py
better_web3/contract/abi/disperse.json
better_web3/contract/abi/erc1155.json
better_web3/contract/abi/erc20.json
better_web3/contract/abi/erc721.json
better_web3/contract/abi/multicall_v3.json
better_web3/contract/contract.py
better_web3/contract/disperse.py
better_web3/contract/erc20.py
better_web3/contract/erc721.py
better_web3/contract/multicall.py
better_web3/provider.py
better_web3/utils/__init__.py
better_web3/utils/eth.py
better_web3/utils/file.py
better_web3/utils/other.py
better_web3/wallet.py
better_web3-3.2.1.dist-info/METADATA
better_web3-3.2.1.dist-info/WHEEL
better_web3-3.2.1.dist-info/RECORD
