Metadata-Version: 2.1
Name: better-web3
Version: 3.2.1
Summary: Chains, Contracts, batch calls and other Web3 stuff!
Home-page: https://github.com/alenkimov/better_web3
Author: Alen
Author-email: alen.kimov@gmail.com
Requires-Python: >=3.11,<4.0
Classifier: Programming Language :: Python :: 3
Classifier: Programming Language :: Python :: 3.11
Classifier: Programming Language :: Python :: 3.12
Requires-Dist: web3 (>=6,<7)
Project-URL: Repository, https://github.com/alenkimov/better_web3
